[{"__type":"AjaxControlToolkit.CascadingDropDownNameValue","name":"అనసభధ్ర","value":"207019","isDefaultValue":false},{"__type":"AjaxControlToolkit.CascadingDropDownNameValue","name":"అలగరువు","value":"207003","isDefaultValue":false},{"__type":"AjaxControlToolkit.CascadingDropDownNameValue","name":"ఎర్రసామంతవలస","value":"207008","isDefaultValue":false},{"__type":"AjaxControlToolkit.CascadingDropDownNameValue","name":"కొండపల్లివలస","value":"207029","isDefaultValue":false},{"__type":"AjaxControlToolkit.CascadingDropDownNameValue","name":"కొండబుచ్చంపేట","value":"207035","isDefaultValue":false},{"__type":"AjaxControlToolkit.CascadingDropDownNameValue","name":"కొండరాజేరు","value":"207042","isDefaultValue":false},{"__type":"AjaxControlToolkit.CascadingDropDownNameValue","name":"కోన","value":"207036","isDefaultValue":false},{"__type":"AjaxControlToolkit.CascadingDropDownNameValue","name":"కన్నంపేట","value":"207054","isDefaultValue":false},{"__type":"AjaxControlToolkit.CascadingDropDownNameValue","name":"కొయ్యానపేట","value":"207040","isDefaultValue":false},{"__type":"AjaxControlToolkit.CascadingDropDownNameValue","name":"కవిరిపల్లి","value":"207033","isDefaultValue":false},{"__type":"AjaxControlToolkit.CascadingDropDownNameValue","name":"కాశీపట్నం","value":"207043","isDefaultValue":false},{"__type":"AjaxControlToolkit.CascadingDropDownNameValue","name":"ఖవిరివలస","value":"207013","isDefaultValue":false},{"__type":"AjaxControlToolkit.CascadingDropDownNameValue","name":"గోపాలపురం","value":"207023","isDefaultValue":false},{"__type":"AjaxControlToolkit.CascadingDropDownNameValue","name":"గుంటభధ్ర","value":"207006","isDefaultValue":false},{"__type":"AjaxControlToolkit.CascadingDropDownNameValue","name":"చంద్రయ్యపేట","value":"207041","isDefaultValue":false},{"__type":"AjaxControlToolkit.CascadingDropDownNameValue","name":"చిన్నంరాజువలస","value":"207034","isDefaultValue":false},{"__type":"AjaxControlToolkit.CascadingDropDownNameValue","name":"చప్పబుచ్చంపేట","value":"207052","isDefaultValue":false},{"__type":"AjaxControlToolkit.CascadingDropDownNameValue","name":"చెముడు","value":"207049","isDefaultValue":false},{"__type":"AjaxControlToolkit.CascadingDropDownNameValue","name":"తోటవలస","value":"207031","isDefaultValue":false},{"__type":"AjaxControlToolkit.CascadingDropDownNameValue","name":"తూరుమామిడి","value":"207038","isDefaultValue":false},{"__type":"AjaxControlToolkit.CascadingDropDownNameValue","name":"దబ్బగడ్డ","value":"207024","isDefaultValue":false},{"__type":"AjaxControlToolkit.CascadingDropDownNameValue","name":"దుగ్గేరు","value":"207005","isDefaultValue":false},{"__type":"AjaxControlToolkit.CascadingDropDownNameValue","name":"నంద","value":"207011","isDefaultValue":false},{"__type":"AjaxControlToolkit.CascadingDropDownNameValue","name":"నందకత్తుల఼఼ఘా఼శిల","value":"207015","isDefaultValue":false},{"__type":"AjaxControlToolkit.CascadingDropDownNameValue","name":"నగుల్లదబ్బగడ్డ","value":"207018","isDefaultValue":false},{"__type":"AjaxControlToolkit.CascadingDropDownNameValue","name":"నారాయణరామచంధ్రరాజపురం","value":"207046","isDefaultValue":false},{"__type":"AjaxControlToolkit.CascadingDropDownNameValue","name":"పీట్లవలస","value":"207026","isDefaultValue":false},{"__type":"AjaxControlToolkit.CascadingDropDownNameValue","name":"పెదఘాశిల","value":"207014","isDefaultValue":false},{"__type":"AjaxControlToolkit.CascadingDropDownNameValue","name":"పెదవూటగెడ్డ","value":"207009","isDefaultValue":false},{"__type":"AjaxControlToolkit.CascadingDropDownNameValue","name":"పనసభధ్ర","value":"207007","isDefaultValue":false},{"__type":"AjaxControlToolkit.CascadingDropDownNameValue","name":"పాపయ్యవలస","value":"207044","isDefaultValue":false},{"__type":"AjaxControlToolkit.CascadingDropDownNameValue","name":"పాయకపాడు","value":"207051","isDefaultValue":false},{"__type":"AjaxControlToolkit.CascadingDropDownNameValue","name":"బంగారువలస","value":"207025","isDefaultValue":false},{"__type":"AjaxControlToolkit.CascadingDropDownNameValue","name":"బంటుమక్కువ","value":"207048","isDefaultValue":false},{"__type":"AjaxControlToolkit.CascadingDropDownNameValue","name":"బట్టివలస","value":"207027","isDefaultValue":false},{"__type":"AjaxControlToolkit.CascadingDropDownNameValue","name":"బీరమాసి","value":"207010","isDefaultValue":false},{"__type":"AjaxControlToolkit.CascadingDropDownNameValue","name":"బెలుగొండ","value":"207001","isDefaultValue":false},{"__type":"AjaxControlToolkit.CascadingDropDownNameValue","name":"మెండంగి","value":"207002","isDefaultValue":false},{"__type":"AjaxControlToolkit.CascadingDropDownNameValue","name":"మక్కువ village","value":"207047","isDefaultValue":false},{"__type":"AjaxControlToolkit.CascadingDropDownNameValue","name":"మార్కొండపుట్టి","value":"207016","isDefaultValue":false},{"__type":"AjaxControlToolkit.CascadingDropDownNameValue","name":"ములక్కాయవలస","value":"207045","isDefaultValue":false},{"__type":"AjaxControlToolkit.CascadingDropDownNameValue","name":"మూకవలస","value":"207050","isDefaultValue":false},{"__type":"AjaxControlToolkit.CascadingDropDownNameValue","name":"మూలవలస","value":"207004","isDefaultValue":false},{"__type":"AjaxControlToolkit.CascadingDropDownNameValue","name":"లోవరఖండి","value":"207021","isDefaultValue":false},{"__type":"AjaxControlToolkit.CascadingDropDownNameValue","name":"వెంకంపేట","value":"207053","isDefaultValue":false},{"__type":"AjaxControlToolkit.CascadingDropDownNameValue","name":"వెంకటభైరిపురం","value":"207039","isDefaultValue":false},{"__type":"AjaxControlToolkit.CascadingDropDownNameValue","name":"విజయరాంపురము","value":"207020","isDefaultValue":false},{"__type":"AjaxControlToolkit.CascadingDropDownNameValue","name":"శంబర","value":"207030","isDefaultValue":false},{"__type":"AjaxControlToolkit.CascadingDropDownNameValue","name":"శిర్లాం","value":"207022","isDefaultValue":false},{"__type":"AjaxControlToolkit.CascadingDropDownNameValue","name":"సింగందొరవలస","value":"207028","isDefaultValue":false},{"__type":"AjaxControlToolkit.CascadingDropDownNameValue","name":"సంతేశ్వరం","value":"207037","isDefaultValue":false},{"__type":"AjaxControlToolkit.CascadingDropDownNameValue","name":"సన్యాసిరాజపురం@మరిపివలస","value":"207032","isDefaultValue":false},{"__type":"AjaxControlToolkit.CascadingDropDownNameValue","name":"సీబిల్లిపెద్దవలస","value":"207012","isDefaultValue":false},{"__type":"AjaxControlToolkit.CascadingDropDownNameValue","name":"సరాయివలస","value":"207017","isDefaultValue":false}]