[{"__type":"AjaxControlToolkit.CascadingDropDownNameValue","name":"అక్కరపాక","value":"944018","isDefaultValue":false},{"__type":"AjaxControlToolkit.CascadingDropDownNameValue","name":"అడపాముడి","value":"944025","isDefaultValue":false},{"__type":"AjaxControlToolkit.CascadingDropDownNameValue","name":"అన్నేగోట్టం","value":"944009","isDefaultValue":false},{"__type":"AjaxControlToolkit.CascadingDropDownNameValue","name":"అనేపూడి","value":"944020","isDefaultValue":false},{"__type":"AjaxControlToolkit.CascadingDropDownNameValue","name":"అయ్యపాలెం","value":"944038","isDefaultValue":false},{"__type":"AjaxControlToolkit.CascadingDropDownNameValue","name":"ఉచ్చూరు","value":"944032","isDefaultValue":false},{"__type":"AjaxControlToolkit.CascadingDropDownNameValue","name":"ఏకొల్లు","value":"944017","isDefaultValue":false},{"__type":"AjaxControlToolkit.CascadingDropDownNameValue","name":"కె.డి. కండ్రిగ","value":"944008","isDefaultValue":false},{"__type":"AjaxControlToolkit.CascadingDropDownNameValue","name":"కట్టువపల్లి","value":"944006","isDefaultValue":false},{"__type":"AjaxControlToolkit.CascadingDropDownNameValue","name":"కోత్తపల్లి","value":"944004","isDefaultValue":false},{"__type":"AjaxControlToolkit.CascadingDropDownNameValue","name":"కారికాడు","value":"944007","isDefaultValue":false},{"__type":"AjaxControlToolkit.CascadingDropDownNameValue","name":"కరటాముడి","value":"944010","isDefaultValue":false},{"__type":"AjaxControlToolkit.CascadingDropDownNameValue","name":"కల్లూరు","value":"944021","isDefaultValue":false},{"__type":"AjaxControlToolkit.CascadingDropDownNameValue","name":"కల్లూరు కండ్రిగ","value":"944022","isDefaultValue":false},{"__type":"AjaxControlToolkit.CascadingDropDownNameValue","name":"చందనమూడి","value":"944040","isDefaultValue":false},{"__type":"AjaxControlToolkit.CascadingDropDownNameValue","name":"తొగరమూడి","value":"944041","isDefaultValue":false},{"__type":"AjaxControlToolkit.CascadingDropDownNameValue","name":"తనయాలి","value":"944029","isDefaultValue":false},{"__type":"AjaxControlToolkit.CascadingDropDownNameValue","name":"తల్లంపాడు","value":"944037","isDefaultValue":false},{"__type":"AjaxControlToolkit.CascadingDropDownNameValue","name":"దామరాయకండ్రిగ","value":"944019","isDefaultValue":false},{"__type":"AjaxControlToolkit.CascadingDropDownNameValue","name":"నేలపట్టు","value":"944014","isDefaultValue":false},{"__type":"AjaxControlToolkit.CascadingDropDownNameValue","name":"నెలబల్లి","value":"944001","isDefaultValue":false},{"__type":"AjaxControlToolkit.CascadingDropDownNameValue","name":"నేల్లూరుపల్లి","value":"944002","isDefaultValue":false},{"__type":"AjaxControlToolkit.CascadingDropDownNameValue","name":"పడమటి కండ్రిగ","value":"944012","isDefaultValue":false},{"__type":"AjaxControlToolkit.CascadingDropDownNameValue","name":"పూలతోట","value":"944011","isDefaultValue":false},{"__type":"AjaxControlToolkit.CascadingDropDownNameValue","name":"బురదమడుగు","value":"944034","isDefaultValue":false},{"__type":"AjaxControlToolkit.CascadingDropDownNameValue","name":"బూదూరు","value":"944030","isDefaultValue":false},{"__type":"AjaxControlToolkit.CascadingDropDownNameValue","name":"మీజూరు","value":"944045","isDefaultValue":false},{"__type":"AjaxControlToolkit.CascadingDropDownNameValue","name":"మోదుగులపాలెం","value":"944035","isDefaultValue":false},{"__type":"AjaxControlToolkit.CascadingDropDownNameValue","name":"మినమనమూడి","value":"944039","isDefaultValue":false},{"__type":"AjaxControlToolkit.CascadingDropDownNameValue","name":"మానేరి","value":"944043","isDefaultValue":false},{"__type":"AjaxControlToolkit.CascadingDropDownNameValue","name":"మైలాంగం","value":"944013","isDefaultValue":false},{"__type":"AjaxControlToolkit.CascadingDropDownNameValue","name":"మల్లయ్య పాలెం","value":"944044","isDefaultValue":false},{"__type":"AjaxControlToolkit.CascadingDropDownNameValue","name":"మేలుపాక","value":"944027","isDefaultValue":false},{"__type":"AjaxControlToolkit.CascadingDropDownNameValue","name":"మావిళ్ళపాడు","value":"944028","isDefaultValue":false},{"__type":"AjaxControlToolkit.CascadingDropDownNameValue","name":"ముచ్చలగుంట","value":"944003","isDefaultValue":false},{"__type":"AjaxControlToolkit.CascadingDropDownNameValue","name":"లింగంపాడు","value":"944036","isDefaultValue":false},{"__type":"AjaxControlToolkit.CascadingDropDownNameValue","name":"వేంగమాంబపురం","value":"944015","isDefaultValue":false},{"__type":"AjaxControlToolkit.CascadingDropDownNameValue","name":"వేటగిరి పాలెం","value":"944033","isDefaultValue":false},{"__type":"AjaxControlToolkit.CascadingDropDownNameValue","name":"వేణుంబాక","value":"944016","isDefaultValue":false},{"__type":"AjaxControlToolkit.CascadingDropDownNameValue","name":"వెదురుపట్టు","value":"944031","isDefaultValue":false},{"__type":"AjaxControlToolkit.CascadingDropDownNameValue","name":"వేలుకాడు","value":"944023","isDefaultValue":false},{"__type":"AjaxControlToolkit.CascadingDropDownNameValue","name":"శ్రీదనమల్లి","value":"944042","isDefaultValue":false},{"__type":"AjaxControlToolkit.CascadingDropDownNameValue","name":"సింగన్నలతూరు","value":"944005","isDefaultValue":false},{"__type":"AjaxControlToolkit.CascadingDropDownNameValue","name":"సూరగుంట తాగేలు","value":"944024","isDefaultValue":false},{"__type":"AjaxControlToolkit.CascadingDropDownNameValue","name":"సూరపు అగ్రహారం","value":"944026","isDefaultValue":false}]