[{"__type":"AjaxControlToolkit.CascadingDropDownNameValue","name":"కోటావూరు","value":"1005009","isDefaultValue":false},{"__type":"AjaxControlToolkit.CascadingDropDownNameValue","name":"గట్టు","value":"1005005","isDefaultValue":false},{"__type":"AjaxControlToolkit.CascadingDropDownNameValue","name":"గొల్లపల్లె","value":"1005008","isDefaultValue":false},{"__type":"AjaxControlToolkit.CascadingDropDownNameValue","name":"గుమ్మసముద్రం","value":"1005001","isDefaultValue":false},{"__type":"AjaxControlToolkit.CascadingDropDownNameValue","name":"తుమ్మనంగుట్ట","value":"1005007","isDefaultValue":false},{"__type":"AjaxControlToolkit.CascadingDropDownNameValue","name":"బి.కొత్తకోట","value":"1005002","isDefaultValue":false},{"__type":"AjaxControlToolkit.CascadingDropDownNameValue","name":"బడికాయలపల్లె","value":"1005004","isDefaultValue":false},{"__type":"AjaxControlToolkit.CascadingDropDownNameValue","name":"బయ్యప్పగారిపల్లె","value":"1005006","isDefaultValue":false},{"__type":"AjaxControlToolkit.CascadingDropDownNameValue","name":"బీరంగి","value":"1005003","isDefaultValue":false}]