[{"__type":"AjaxControlToolkit.CascadingDropDownNameValue","name":"కొండక్రిందఅగ్రహరం","value":"1226012","isDefaultValue":false},{"__type":"AjaxControlToolkit.CascadingDropDownNameValue","name":"కొర్రపాడు","value":"1226004","isDefaultValue":false},{"__type":"AjaxControlToolkit.CascadingDropDownNameValue","name":"గోవిందపల్లి","value":"1226009","isDefaultValue":false},{"__type":"AjaxControlToolkit.CascadingDropDownNameValue","name":"చదుల్ల","value":"1226003","isDefaultValue":false},{"__type":"AjaxControlToolkit.CascadingDropDownNameValue","name":"చెన్నంపల్లి","value":"1226005","isDefaultValue":false},{"__type":"AjaxControlToolkit.CascadingDropDownNameValue","name":"చెన్నరాయనిపల్లి","value":"1226007","isDefaultValue":false},{"__type":"AjaxControlToolkit.CascadingDropDownNameValue","name":"జంతులూరు","value":"1226002","isDefaultValue":false},{"__type":"AjaxControlToolkit.CascadingDropDownNameValue","name":"డండువారిపల్లి","value":"1226013","isDefaultValue":false},{"__type":"AjaxControlToolkit.CascadingDropDownNameValue","name":"పొడరాల్ల","value":"1226001","isDefaultValue":false},{"__type":"AjaxControlToolkit.CascadingDropDownNameValue","name":"బోడిగానిదొడ్డి (రోటరిపురం)","value":"1226006","isDefaultValue":false},{"__type":"AjaxControlToolkit.CascadingDropDownNameValue","name":"బుక్కరాయసముద్రం","value":"1226010","isDefaultValue":false},{"__type":"AjaxControlToolkit.CascadingDropDownNameValue","name":"రెడ్డిపల్లి","value":"1226011","isDefaultValue":false},{"__type":"AjaxControlToolkit.CascadingDropDownNameValue","name":"శిద్దరాంపురం","value":"1226014","isDefaultValue":false},{"__type":"AjaxControlToolkit.CascadingDropDownNameValue","name":"సిద్దంపేట","value":"1226008","isDefaultValue":false}]