[{"__type":"AjaxControlToolkit.CascadingDropDownNameValue","name":"అప్పలరాజుగూడెం","value":"508004","isDefaultValue":false},{"__type":"AjaxControlToolkit.CascadingDropDownNameValue","name":"అల్లంచర్లరాజుపాలెం","value":"508023","isDefaultValue":false},{"__type":"AjaxControlToolkit.CascadingDropDownNameValue","name":"ఈపిగుంట","value":"508009","isDefaultValue":false},{"__type":"AjaxControlToolkit.CascadingDropDownNameValue","name":"కేతవరము","value":"508015","isDefaultValue":false},{"__type":"AjaxControlToolkit.CascadingDropDownNameValue","name":"కౌల్లివారిగుడెం","value":"508001","isDefaultValue":false},{"__type":"AjaxControlToolkit.CascadingDropDownNameValue","name":"కృష్ణపురం","value":"508005","isDefaultValue":false},{"__type":"AjaxControlToolkit.CascadingDropDownNameValue","name":"కృష్ణరావుపాలెం","value":"508020","isDefaultValue":false},{"__type":"AjaxControlToolkit.CascadingDropDownNameValue","name":"గుడ్లపల్లి","value":"508017","isDefaultValue":false},{"__type":"AjaxControlToolkit.CascadingDropDownNameValue","name":"గురవాయిగూడెం","value":"508008","isDefaultValue":false},{"__type":"AjaxControlToolkit.CascadingDropDownNameValue","name":"టి.నరసాపురం","value":"508007","isDefaultValue":false},{"__type":"AjaxControlToolkit.CascadingDropDownNameValue","name":"తెడ్లం","value":"508019","isDefaultValue":false},{"__type":"AjaxControlToolkit.CascadingDropDownNameValue","name":"తిరుమలదేవి పేట","value":"508010","isDefaultValue":false},{"__type":"AjaxControlToolkit.CascadingDropDownNameValue","name":"బండివారిగూడెం","value":"508003","isDefaultValue":false},{"__type":"AjaxControlToolkit.CascadingDropDownNameValue","name":"బందంచర్ల","value":"508016","isDefaultValue":false},{"__type":"AjaxControlToolkit.CascadingDropDownNameValue","name":"బౌర్రంపాలెం","value":"508012","isDefaultValue":false},{"__type":"AjaxControlToolkit.CascadingDropDownNameValue","name":"మక్కినవారిగూడెం","value":"508002","isDefaultValue":false},{"__type":"AjaxControlToolkit.CascadingDropDownNameValue","name":"రాజుపోతేపల్లి","value":"508018","isDefaultValue":false},{"__type":"AjaxControlToolkit.CascadingDropDownNameValue","name":"రామన్నపాలెం","value":"508011","isDefaultValue":false},{"__type":"AjaxControlToolkit.CascadingDropDownNameValue","name":"లింగరావుపాలెం","value":"508022","isDefaultValue":false},{"__type":"AjaxControlToolkit.CascadingDropDownNameValue","name":"వాకలపూడి","value":"508006","isDefaultValue":false},{"__type":"AjaxControlToolkit.CascadingDropDownNameValue","name":"వెలగపాడు","value":"508014","isDefaultValue":false},{"__type":"AjaxControlToolkit.CascadingDropDownNameValue","name":"వల్లంపట్ల","value":"508013","isDefaultValue":false},{"__type":"AjaxControlToolkit.CascadingDropDownNameValue","name":"శ్రీరామవరం","value":"508021","isDefaultValue":false}]