[{"__type":"AjaxControlToolkit.CascadingDropDownNameValue","name":"అదపాక","value":"106007","isDefaultValue":false},{"__type":"AjaxControlToolkit.CascadingDropDownNameValue","name":"అప్పాపురం","value":"106012","isDefaultValue":false},{"__type":"AjaxControlToolkit.CascadingDropDownNameValue","name":"కొండకుంకాం","value":"106003","isDefaultValue":false},{"__type":"AjaxControlToolkit.CascadingDropDownNameValue","name":"కొత్తకోట","value":"106008","isDefaultValue":false},{"__type":"AjaxControlToolkit.CascadingDropDownNameValue","name":"కొత్తకుంకాం","value":"106002","isDefaultValue":false},{"__type":"AjaxControlToolkit.CascadingDropDownNameValue","name":"కేశవరాయపురం","value":"106028","isDefaultValue":false},{"__type":"AjaxControlToolkit.CascadingDropDownNameValue","name":"కేశవరాయునిపాలెం","value":"106039","isDefaultValue":false},{"__type":"AjaxControlToolkit.CascadingDropDownNameValue","name":"గోవిందపురం","value":"106013","isDefaultValue":false},{"__type":"AjaxControlToolkit.CascadingDropDownNameValue","name":"గుమడాం","value":"106033","isDefaultValue":false},{"__type":"AjaxControlToolkit.CascadingDropDownNameValue","name":"గురుగుబిల్లి","value":"106016","isDefaultValue":false},{"__type":"AjaxControlToolkit.CascadingDropDownNameValue","name":"గూడెంగొలుగువలస","value":"106027","isDefaultValue":false},{"__type":"AjaxControlToolkit.CascadingDropDownNameValue","name":"చెల్లయ్యమ్మ అగ్రహరం","value":"106040","isDefaultValue":false},{"__type":"AjaxControlToolkit.CascadingDropDownNameValue","name":"తామాడ","value":"106034","isDefaultValue":false},{"__type":"AjaxControlToolkit.CascadingDropDownNameValue","name":"తాళ్లవలస","value":"106026","isDefaultValue":false},{"__type":"AjaxControlToolkit.CascadingDropDownNameValue","name":"నాగంపాలెం","value":"106032","isDefaultValue":false},{"__type":"AjaxControlToolkit.CascadingDropDownNameValue","name":"నేతేరు","value":"106037","isDefaultValue":false},{"__type":"AjaxControlToolkit.CascadingDropDownNameValue","name":"నీలాపురం","value":"106023","isDefaultValue":false},{"__type":"AjaxControlToolkit.CascadingDropDownNameValue","name":"పైడాయవలస","value":"106001","isDefaultValue":false},{"__type":"AjaxControlToolkit.CascadingDropDownNameValue","name":"పాతకుంకాం","value":"106004","isDefaultValue":false},{"__type":"AjaxControlToolkit.CascadingDropDownNameValue","name":"పోతయ్యవలస","value":"106009","isDefaultValue":false},{"__type":"AjaxControlToolkit.CascadingDropDownNameValue","name":"పెద్దకొత్తపల్లి","value":"106006","isDefaultValue":false},{"__type":"AjaxControlToolkit.CascadingDropDownNameValue","name":"పెద్దలింగాలవలస","value":"106010","isDefaultValue":false},{"__type":"AjaxControlToolkit.CascadingDropDownNameValue","name":"పెదరావుపల్లి","value":"106020","isDefaultValue":false},{"__type":"AjaxControlToolkit.CascadingDropDownNameValue","name":"బెజ్జిపురం","value":"106018","isDefaultValue":false},{"__type":"AjaxControlToolkit.CascadingDropDownNameValue","name":"బుడతవలస","value":"106022","isDefaultValue":false},{"__type":"AjaxControlToolkit.CascadingDropDownNameValue","name":"బుడుమూరు","value":"106019","isDefaultValue":false},{"__type":"AjaxControlToolkit.CascadingDropDownNameValue","name":"భరణికాం","value":"106014","isDefaultValue":false},{"__type":"AjaxControlToolkit.CascadingDropDownNameValue","name":"మురపాక","value":"106021","isDefaultValue":false},{"__type":"AjaxControlToolkit.CascadingDropDownNameValue","name":"రేగపాలేం","value":"106036","isDefaultValue":false},{"__type":"AjaxControlToolkit.CascadingDropDownNameValue","name":"రావివలస","value":"106029","isDefaultValue":false},{"__type":"AjaxControlToolkit.CascadingDropDownNameValue","name":"లక్ష్మీపురం","value":"106035","isDefaultValue":false},{"__type":"AjaxControlToolkit.CascadingDropDownNameValue","name":"లోపెంట","value":"106038","isDefaultValue":false},{"__type":"AjaxControlToolkit.CascadingDropDownNameValue","name":"లావేరు","value":"106015","isDefaultValue":false},{"__type":"AjaxControlToolkit.CascadingDropDownNameValue","name":"వెంకటపురం","value":"106011","isDefaultValue":false},{"__type":"AjaxControlToolkit.CascadingDropDownNameValue","name":"వెంకటాపురం","value":"106024","isDefaultValue":false},{"__type":"AjaxControlToolkit.CascadingDropDownNameValue","name":"విజయరాంపురం","value":"106005","isDefaultValue":false},{"__type":"AjaxControlToolkit.CascadingDropDownNameValue","name":"వేణుగోపాలపురం","value":"106031","isDefaultValue":false},{"__type":"AjaxControlToolkit.CascadingDropDownNameValue","name":"శిగిరికొత్తపల్లి","value":"106017","isDefaultValue":false},{"__type":"AjaxControlToolkit.CascadingDropDownNameValue","name":"శీర్లపాలెం","value":"106030","isDefaultValue":false},{"__type":"AjaxControlToolkit.CascadingDropDownNameValue","name":"సహపురం","value":"106041","isDefaultValue":false},{"__type":"AjaxControlToolkit.CascadingDropDownNameValue","name":"సుభద్రాపురం","value":"106025","isDefaultValue":false},{"__type":"AjaxControlToolkit.CascadingDropDownNameValue","name":"హనుమంతపురం","value":"106042","isDefaultValue":false}]